mars_weather_api/__init__.py
mars_weather_api/mars_weather_api.py
mars_weather_api-0.1.9.dist-info/licenses/LICENSE
mars_weather_api-0.1.9.dist-info/METADATA
mars_weather_api-0.1.9.dist-info/WHEEL
mars_weather_api-0.1.9.dist-info/top_level.txt
mars_weather_api-0.1.9.dist-info/RECORD
